[
  {
    "name": "kepo",
    "message": "anjay",
    "avatar": "https://raw.githubusercontent.com/RavageStore/aima/main/image/1760426470550-kepo.jpg",
    "time": "2025-10-14T07:21:12.166Z",
    "like": 0,
    "pin": true,
    "reply": []
  },
  {
    "name": "Daffa",
    "message": "Hai Cantik",
    "avatar": "https://raw.githubusercontent.com/RavageStore/aima/main/image/1760426230730-Daffa.jpg",
    "time": "2025-10-14T07:17:12.892Z",
    "like": 1,
    "pin": true,
    "reply": [
      {
        "replyname": "aima",
        "replymessage": "apa sayang"
      }
    ]
  },
  {
    "name": "bang",
    "message": "sat",
    "avatar": "",
    "time": "2025-10-14T07:23:02.884Z",
    "like": 0,
    "pin": false,
    "reply": []
  }
]